[{"caption":{"en":"The image depicts a protest scene with multiple vehicles, including buses and cars"},"counts":{"person":14},"index":5,"objects":["person"]},{"caption":{"en":"The image shows a nighttime scene with various vehicles and people"},"counts":{"bus":1,"car":3,"person":15},"index":3330,"objects":["bus","car","person"]},{"caption":{"en":"The image shows a nighttime scene with various lights"},"counts":{},"index":5130,"objects":[]},{"caption":{"en":"The image shows a red car driving on the street at night, with traffic lights and trees in view"},"counts":{"car":1},"index":6930,"objects":["car"]},{"caption":{"en":"The image shows a night scene with bright lights and blurred vehicles"},"counts":{},"index":8880,"objects":[]},{"caption":{"en":"The image shows a nighttime scene with police vehicles and lights on an overpass, likely indicating some form of public event or protest"},"counts":{},"index":10705,"objects":[]}]