[{"caption":{"en":"The image shows a protest scene with people walking on the street, surrounded by smoke and possibly tear gas"},"counts":{},"index":5,"objects":[]},{"caption":{"en":"The image shows a large group of people gathered in an open area"},"counts":{},"index":1865,"objects":[]},{"caption":{"en":"The image shows a large group of people gathered in an open area"},"counts":{"person":9},"index":4305,"objects":["person"]},{"caption":{"en":"The image is a video clip showing an outdoor event with many people"},"counts":{},"index":6105,"objects":[]}]