[{"caption":{"en":"The image is a blurry, out-of-focus photograph with indistinct details that suggest it was taken during an event or movement"},"counts":{"stairs":1},"index":1660,"objects":["stairs"]},{"caption":{"en":"The image is a blurry video clip with indistinct figures and motion"},"counts":{},"index":15110,"objects":[]},{"caption":{"en":"The image shows a scene of people walking on what appears to be an outdoor area"},"counts":{"person":3},"index":20380,"objects":["person"]},{"caption":{"en":"The image shows a person walking in an indoor setting"},"counts":{"person":1},"index":22185,"objects":["person"]},{"caption":{"en":"The image shows a group of people gathered in an indoor space"},"counts":{"person":5},"index":24710,"objects":["person"]},{"caption":{"en":"The image shows a blurry scene with people walking through what appears to be an urban environment"},"counts":{},"index":26985,"objects":[]},{"caption":{"en":"The image is not related to sports or winter"},"counts":{},"index":28810,"objects":[]},{"caption":{"en":"The image shows a blurry scene with various objects, including chairs and what appears to be an outdoor setting"},"counts":{"stairs":1},"index":31445,"objects":["stairs"]},{"caption":{"en":"The image shows a blurry scene with rows of chairs arranged in an indoor setting"},"counts":{},"index":38085,"objects":[]},{"caption":{"en":"The image is a blurry video clip from 08-123, taken at the time of Dom"},"counts":{"window":1},"index":43050,"objects":["window"]},{"caption":{"en":"The image is a blurry video clip taken during what appears to be an outdoor protest, with the word \"PRESET3\" and some text about it being captured on August 1st in Brazil"},"counts":{"window":2},"index":47650,"objects":["window"]}]