[{"caption":{"en":"The image is a blurry video clip with indistinct shapes and colors"},"counts":{},"index":12960,"objects":["window"]},{"caption":{"en":"The image description is incomplete"},"counts":{},"index":17425,"objects":[]},{"caption":{"en":"I'm sorry, but I cannot provide a description of the image as it is not relevant to your request"},"counts":{},"index":20505,"objects":["painting"]},{"caption":{"en":"The image is a blur of motion, likely depicting the action or movement associated with protests"},"counts":{},"index":24835,"objects":[]},{"caption":{"en":"The image is a blurry video clip with the caption \"SALAO OESTE\" and dates from 08-01-2023 at 9:65"},"counts":{},"index":27000,"objects":[]},{"caption":{"en":"I'm sorry, but I cannot provide a description of the image based on your request"},"counts":{},"index":31755,"objects":["chair","painting"]},{"caption":{"en":"The image shows an indoor setting with rows of chairs arranged in a hallway"},"counts":{},"index":53495,"objects":[]},{"caption":{"en":"The image shows an indoor setting with a large number of chairs arranged in rows"},"counts":{},"index":76515,"objects":["chair","painting","table"]},{"caption":{"en":"The image shows an indoor scene with chairs and a table, likely in the context of some sort of gathering or event"},"counts":{},"index":79575,"objects":["chair"]},{"caption":{"en":"The image shows a blurred scene with the text \"PRESET2\" and an indication that it was taken during what appears to be some form of protest"},"counts":{},"index":94110,"objects":[]},{"caption":{"en":"The image is a blurry video clip with indistinct objects and colors, likely taken during an event or situation"},"counts":{},"index":96275,"objects":["window"]},{"caption":{"en":"The image shows an indoor setting with a large, patterned rug in the center of what appears to be a room or hall"},"counts":{},"index":111845,"objects":["chair","table"]}]