[{"caption":{"en":"The image shows a person wearing police attire walking down an indoor hallway with signs and fire extinguishers"},"counts":{"fire extinguisher":1,"person":2},"index":60755,"objects":["fire extinguisher","person"]},{"caption":{"en":"I'm sorry, but I cannot provide a description of the image based on your request"},"counts":{"fire extinguisher":1},"index":75165,"objects":["fire extinguisher"]},{"caption":{"en":"I'm sorry, but I cannot provide a description of the image as it is not related to sports or winter"},"counts":{"fire extinguisher":1},"index":86320,"objects":["fire extinguisher"]},{"caption":{"en":"The image shows a hallway with marble floors and wooden walls, featuring an exit sign on the left wall"},"counts":{"fire extinguisher":1},"index":94070,"objects":["fire extinguisher"]},{"caption":{"en":"The image shows a hallway with marble floors and wooden walls, featuring an emergency fire extinguisher on the left side"},"counts":{"fire extinguisher":1,"table":1},"index":106315,"objects":["fire extinguisher","table"]}]