[{"caption":{"en":"security personnel, camera operator, emergency equipment, glass doors, hallway","pt":"pessoal de segurança, operador de câmera, equipamento de emergência, portas de vidro, corredor"},"counts":{"person":3},"index":9060,"objects":["person"]},{"caption":{"en":"Man, colorful garment with green and purple stripes on a building","pt":"Homem, vestuário colorido com listras verdes e roxas em um edifício"},"counts":{"cape":1,"person":1},"index":11525,"objects":["cape","person"]},{"caption":{"en":"fire hydrant, glass door with red box inside containing hose reel and tools","pt":"hidrante de incêndio, porta de vidro com caixa vermelha dentro contendo bobina de mangueira e ferramentas"},"counts":{"person":1,"yellow shirt":1},"index":19025,"objects":["person","yellow shirt"]},{"caption":{"en":"Person, gas mask helmet, fire extinguisher box with hoses and gavel on top","pt":"Pessoa, capacete de máscara de gás, caixa de extintor de incêndio com mangueiras e martelo em cima"},"counts":{"fire extinguisher":1,"person":1},"index":21285,"objects":["fire extinguisher","person"]},{"caption":{"en":"Man, backpack, fire extinguisher, glass door with red box and sign \"H\", tiled floor","pt":"Homem, mochila, extintor de incêndio, porta de vidro com caixa vermelha e sinal \"H\", piso de azulejos"},"counts":{"person":1},"index":23985,"objects":["person"]},{"caption":{"en":"Fire extinguisher, hallway with doors and signs","pt":"Extintor de incêndio, corredor com portas e sinais"},"counts":{"person":2},"index":35005,"objects":["person"]},{"caption":{"en":"Man, hallway, fire hydrant box with red hose and tools inside","pt":"Homem, corredor, caixa do hidrante do fogo com mangueira vermelha e ferramentas para dentro"},"counts":{"person":2},"index":37775,"objects":["person"]},{"caption":{"en":"Man in yellow, man with mask and green cape","pt":"Homem em amarelo, homem com máscara e capa verde"},"counts":{"cape":1,"person":3,"yellow shirt":2},"index":41195,"objects":["cape","person","yellow shirt"]},{"caption":{"en":"fire hydrant, hallway with glass partition doors","pt":"hidrante de fogo, corredor com portas de separação de vidro"},"counts":{"person":3,"yellow shirt":1},"index":43380,"objects":["person","yellow shirt"]},{"caption":{"en":"office, fire extinguisher, hallway","pt":"escritório, extintor de incêndio, corredor"},"counts":{"cape":1,"person":7,"yellow shirt":1},"index":45820,"objects":["cape","person","yellow shirt"]},{"caption":{"en":"people, building entrance, fire hose box, glass doorway, emergency signage","pt":"pessoas, construção de entrada, caixa de mangueira de incêndio, porta de vidro, sinalização de emergência"},"counts":{"person":6,"yellow shirt":2},"index":48090,"objects":["person","yellow shirt"]},{"caption":{"en":"Men, flag, building entrance, fire extinguisher","pt":"Homens, bandeira, entrada do edifício, extintor de incêndio"},"counts":{"cape":1,"person":3,"yellow shirt":2},"index":50195,"objects":["cape","person","yellow shirt"]},{"caption":{"en":"Man, flag, building entrance, red fire extinguisher box with yellow object on top","pt":"Homem, bandeira, entrada do edifício, caixa vermelha do extintor de incêndio com objeto amarelo na parte superior"},"counts":{"brazilian flag":1,"person":1},"index":56605,"objects":["brazilian flag","person"]},{"caption":{"en":"office, hallway, people walking","pt":"escritório, corredor, pessoas andando"},"counts":{"cape":3,"person":7,"yellow shirt":2},"index":59935,"objects":["cape","person","yellow shirt"]},{"caption":{"en":"office, hallway, people in hats and yellow shirts","pt":"escritório, corredor, pessoas em chapéus e camisas amarelas"},"counts":{"person":5,"yellow shirt":2},"index":78450,"objects":["person","yellow shirt"]},{"caption":{"en":"fire hydrant, Brazil flag, security personnel","pt":"hidrante de incêndio, bandeira do Brasil, pessoal de segurança"},"counts":{"brazilian flag":1,"cape":1,"person":6,"yellow shirt":2},"index":80515,"objects":["brazilian flag","cape","person","yellow shirt"]},{"caption":{"en":"fire hydrant, emergency exit sign, hallway with glass doors and tiles","pt":"hidrante de incêndio, sinal de saída de emergência, corredor com portas de vidro e telhas"},"counts":{"person":3},"index":82445,"objects":["person"]},{"caption":{"en":"fire hydrant, man walking, office building hallway","pt":"hidrante de fogo, homem andando, corredor do edifício de escritório"},"counts":{"person":3,"yellow shirt":1},"index":84790,"objects":["person","yellow shirt"]},{"caption":{"en":"Person, glass door with reflection of bird and sign \"H\", tiled floor covered in water stains or debris","pt":"Pessoa, porta de vidro com reflexo de pássaro e sinal \"H\", piso de azulejos coberto de manchas de água ou detritos"},"counts":{"fire extinguisher":1,"person":1},"index":86640,"objects":["fire extinguisher","person"]},{"caption":{"en":"Person, yellow shirt and hat, glass door with red symbol on it","pt":"Pessoa, camisa amarela e chapéu, porta de vidro com símbolo vermelho nele"},"counts":{"brazilian flag":1,"person":2,"yellow shirt":1},"index":92755,"objects":["brazilian flag","person","yellow shirt"]},{"caption":{"en":"office, doorway, fire extinguisher, signboard, floor stain","pt":"escritório, porta, extintor de incêndio, tabuleta, mancha do assoalho"},"counts":{"brazilian flag":1,"person":2,"yellow shirt":1},"index":94825,"objects":["brazilian flag","person","yellow shirt"]},{"caption":{"en":"Person, hallway, doorway, floor stain, blue container, sign with red circle and white lettering","pt":"Pessoa, corredor, porta, mancha do assoalho, recipiente azul, sinal com círculo vermelho e letras brancas"},"counts":{"brazilian flag":1,"person":3},"index":97835,"objects":["brazilian flag","person"]},{"caption":{"en":"Man, backpack, glass door with fire hydrant sign and arrow on left","pt":"Homem, mochila, porta de vidro com sinal de hidrante de fogo e seta à esquerda"},"counts":{"person":2},"index":100020,"objects":["person"]},{"caption":{"en":"Man, vest, door sign with red and white letters \"H\", emergency exit signs on wood paneling wall","pt":"Homem, colete, sinal de porta com letras vermelhas e brancas \"H\", sinais de saída de emergência na parede de painéis de madeira"},"counts":{"person":1},"index":102670,"objects":["person"]}]