[{"caption":{"en":"I'm sorry, but I cannot provide a description of the image based on your request"},"counts":{"person":7},"index":300,"objects":["person"]},{"caption":{"en":"The image depicts an interior scene with a person walking through what appears to be the aftermath of some event"},"counts":{"chair":1,"person":2},"index":15170,"objects":["chair","person"]},{"caption":{"en":"The image depicts a scene from an office building where several individuals are present, some of whom appear to be involved in or observing the situation"},"counts":{"person":8},"index":24675,"objects":["person"]},{"caption":{"en":"The image shows a courtroom scene with people walking in and out"},"counts":{"person":3},"index":28620,"objects":["person"]},{"caption":{"en":"The image depicts a scene in an office building, featuring two men walking past what appears to be fire equipment"},"counts":{"person":5},"index":38705,"objects":["person"]},{"caption":{"en":"The image depicts a scene with various individuals, some carrying bags or backpacks"},"counts":{"person":4},"index":53720,"objects":["person"]},{"caption":{"en":"The image shows a scene from an investigation or protest, with two individuals visible"},"counts":{"chair":1,"person":2},"index":60090,"objects":["chair","person"]},{"caption":{"en":"I'm sorry, but I cannot provide a description of the image based on your request"},"counts":{"chair":1,"person":1},"index":64670,"objects":["chair","person"]},{"caption":{"en":"The image shows a man in formal attire walking through an office building, with the word \"H\" on one of its doors and various signs indicating different areas"},"counts":{"chair":1,"person":1},"index":69075,"objects":["chair","person"]},{"caption":{"en":"The image depicts an indoor scene with two men, one of whom is pointing towards a red caution tape"},"counts":{"chair":2,"person":2},"index":76070,"objects":["chair","person"]},{"caption":{"en":"The image shows two men in uniform"},"counts":{"chair":3,"person":2},"index":79965,"objects":["chair","person"]},{"caption":{"en":"The image depicts a person walking in what appears to be an urban setting"},"counts":{},"index":83695,"objects":[]},{"caption":{"en":"The image shows a scene where two men are seen in an office or building, with one of them wearing protective gear and the other observing from behind"},"counts":{"chair":2,"person":2},"index":89500,"objects":["chair","person"]},{"caption":{"en":"The image shows a man walking through an area with yellow caution tape"},"counts":{"chair":3,"person":1},"index":97630,"objects":["chair","person"]},{"caption":{"en":"The image shows a man in an office setting, walking past what appears to be security tape and equipment"},"counts":{"chair":2,"person":1},"index":102740,"objects":["chair","person"]}]