[{"caption":{"en":"fire hydrant, emergency doorway, yellow caution tape","pt":"hidrante de incêndio, porta de emergência, fita de advertência amarela"},"counts":{},"index":1190,"objects":[]},{"caption":{"en":"fire hydrant, emergency exit sign 'H', security tape with warning message","pt":"hidrante de incêndio, sinal de saída de emergência 'H', fita de segurança com mensagem de aviso"},"counts":{"person":2},"index":5250,"objects":["person"]},{"caption":{"en":"Men, hallway with glass doors and yellow caution tape","pt":"Homens, corredor com portas de vidro e fita de advertência amarela"},"counts":{"person":2},"index":8555,"objects":["person"]},{"caption":{"en":"fire hydrant, security camera footage, hallway with tape and debris","pt":"hidrante de incêndio, filmagem de câmera de segurança, corredor com fita e detritos"},"counts":{"person":2},"index":15465,"objects":["person"]},{"caption":{"en":"security personnel, emergency scene, tape barrier, building entrance","pt":"pessoal de segurança, cena da emergência, barreira da fita, entrada do edifício"},"counts":{"person":2},"index":17700,"objects":["person"]},{"caption":{"en":"security, officers, building entrance, tape barrier, emergency situation","pt":"segurança, oficiais, entrada do edifício, barreira da fita, situação de emergência"},"counts":{"person":6},"index":21860,"objects":["person"]},{"caption":{"en":"security, investigation scene; people in suits and casual attire","pt":"segurança, cena da investigação; pessoas em ternos e trajes casuais"},"counts":{"cape":1,"person":7},"index":24365,"objects":["cape","person"]},{"caption":{"en":"office, security personnel, emergency exit sign, fire hose cabinet, tape barrier","pt":"escritório, pessoal de segurança, sinal de saída de emergência, armário de mangueira de incêndio, barreira de fita"},"counts":{"person":4},"index":26230,"objects":["person"]},{"caption":{"en":"security, investigation, hallway, doorway, fire hydrant, tape","pt":"segurança, investigação, corredor, entrada, hidrante de incêndio, fita"},"counts":{"person":4},"index":28425,"objects":["person"]},{"caption":{"en":"office, glass door with red tape and fire hose in cabinet","pt":"escritório, porta de vidro com fita vermelha e mangueira de incêndio no armário"},"counts":{"person":2},"index":30775,"objects":["person"]},{"caption":{"en":"woman, man in uniform, emergency equipment cabinet with a red label and an arrow pointing to the left","pt":"mulher, homem uniforme, armário de equipamentos de emergência com uma etiqueta vermelha e uma seta apontando para a esquerda"},"counts":{"person":5},"index":32745,"objects":["person"]},{"caption":{"en":"security, investigation team, hallway with glass doors, emergency equipment box labeled 'H', yellow caution tape","pt":"segurança, equipe de investigação, corredor com portas de vidro, caixa de equipamentos de emergência rotulada 'H', fita de advertência amarela"},"counts":{"person":4},"index":34635,"objects":["person"]},{"caption":{"en":"security, investigation, officers, building entrance, glass door, emergency exit sign","pt":"segurança, investigação, oficiais, entrada do edifício, porta de vidro, sinal de saída de emergência"},"counts":{"person":2},"index":36565,"objects":["person"]},{"caption":{"en":"cops, investigation scene","pt":"polícias, cena da investigação"},"counts":{"person":6},"index":38780,"objects":["person"]},{"caption":{"en":"officers, investigation, building entrance, emergency response","pt":"oficiais, investigação, entrada do edifício, resposta de emergência"},"counts":{"person":5},"index":41120,"objects":["person"]},{"caption":{"en":"security, investigation team, police uniformed officers, glass door with yellow tape","pt":"segurança, equipe de investigação, policiais uniformizados, porta de vidro com fita amarela"},"counts":{"person":4},"index":42955,"objects":["person"]},{"caption":{"en":"security, investigation, building entrance, tape warning sign","pt":"segurança, investigação, entrada do edifício, sinal de aviso de fita"},"counts":{"person":3},"index":44995,"objects":["person"]},{"caption":{"en":"office, hallway, security personnel, investigators, emergency exit sign","pt":"escritório, corredor, pessoal de segurança, investigadores, sinal de saída de emergência"},"counts":{"person":17},"index":47010,"objects":["person"]},{"caption":{"en":"security guard, emergency exit sign, fire hydrant box with hose attached","pt":"guarda de segurança, sinal de saída de emergência, caixa de hidrante de incêndio com mangueira anexada"},"counts":{"person":9},"index":48860,"objects":["person"]},{"caption":{"en":"office, security personnel, emergency exit sign, red hose in box","pt":"escritório, pessoal de segurança, sinal de saída de emergência, mangueira vermelha na caixa"},"counts":{"person":10},"index":50910,"objects":["person"]},{"caption":{"en":"fire hydrant, emergency exit sign, glass door with yellow tape","pt":"hidrante de incêndio, sinal de saída de emergência, porta de vidro com fita amarela"},"counts":{"person":7},"index":52960,"objects":["person"]}]